bosch_thermostat_http_simulator/__init__.py
bosch_thermostat_http_simulator/bosch_run.py
bosch_thermostat_http_simulator/bosch_scan.py
bosch_thermostat_http_simulator/const.py
bosch_thermostat_http_simulator/encryption.py
bosch_thermostat_http_simulator/version.py
bosch_thermostat_http_simulator-0.0.3.dist-info/LICENSE
bosch_thermostat_http_simulator-0.0.3.dist-info/METADATA
bosch_thermostat_http_simulator-0.0.3.dist-info/WHEEL
bosch_thermostat_http_simulator-0.0.3.dist-info/entry_points.txt
bosch_thermostat_http_simulator-0.0.3.dist-info/top_level.txt
bosch_thermostat_http_simulator-0.0.3.dist-info/RECORD
